mcp_server/__init__.py
mcp_server/server.py
runwise/__init__.py
runwise/anomalies.py
runwise/cli.py
runwise/config.py
runwise/core.py
runwise/py.typed
runwise/sparklines.py
runwise/tensorboard.py
runwise/wandb_api.py
runwise/formatters/__init__.py
runwise/formatters/markdown.py
runwise/parsers/__init__.py
runwise-0.4.0.dist-info/licenses/LICENSE
runwise-0.4.0.dist-info/METADATA
runwise-0.4.0.dist-info/WHEEL
runwise-0.4.0.dist-info/entry_points.txt
runwise-0.4.0.dist-info/top_level.txt
runwise-0.4.0.dist-info/RECORD
