Metadata-Version: 2.4
Name: runwise
Version: 0.4.0
Summary: Token-efficient ML training run analysis for AI agents
Author: PepTRM Team
License-Expression: MIT
Project-URL: Homepage, https://github.com/jasegehring/runwise
Project-URL: Documentation, https://github.com/jasegehring/runwise#readme
Project-URL: Repository, https://github.com/jasegehring/runwise
Project-URL: Issues, https://github.com/jasegehring/runwise/issues
Keywords: machine-learning,wandb,training,analysis,llm,ai-assistant,mcp
Classifier: Development Status :: 3 - Alpha
Classifier: Intended Audience :: Developers
Classifier: Intended Audience :: Science/Research
Classifier: Programming Language :: Python :: 3
Classifier: Programming Language :: Python :: 3.10
Classifier: Programming Language :: Python :: 3.11
Classifier: Programming Language :: Python :: 3.12
Classifier: Topic :: Scientific/Engineering :: Artificial Intelligence
Requires-Python: >=3.10
License-File: LICENSE
Provides-Extra: dev
Requires-Dist: pytest>=7.0; extra == "dev"
Requires-Dist: black; extra == "dev"
Requires-Dist: ruff; extra == "dev"
Dynamic: license-file
